<annotation>
    <folder>training</folder>
    <filename>0e5d4e9c17db22dfd57854a3fd15333aa3ec5e30.png</filename>
    <size>
        <width>1125</width>
        <height>2436</height>
        <depth>3</depth>
    </size>
    <object>
        <name>Switches</name>
        <difficult>0</difficult>
        <bndbox>
            <xmin>929</xmin>
            <ymin>1986</ymin>
            <xmax>1090</xmax>
            <ymax>2083</ymax>
        </bndbox>
    </object>
    <object>
        <name>Switches</name>
        <difficult>0</difficult>
        <bndbox>
            <xmin>926</xmin>
            <ymin>1650</ymin>
            <xmax>1086</xmax>
            <ymax>1751</ymax>
        </bndbox>
    </object>
    <object>
        <name>Radio buttons</name>
        <difficult>0</difficult>
        <bndbox>
            <xmin>1</xmin>
            <ymin>432</ymin>
            <xmax>1125</xmax>
            <ymax>581</ymax>
        </bndbox>
    </object>
    <object>
        <name>Buttons</name>
        <difficult>0</difficult>
        <bndbox>
            <xmin>5</xmin>
            <ymin>115</ymin>
            <xmax>295</xmax>
            <ymax>257</ymax>
        </bndbox>
    </object>
</annotation>