<annotation>
    <folder>training</folder>
    <filename>235f735168de74efcaca05d105acfc2f33c9d2f2.jpeg</filename>
    <size>
        <width>1125</width>
        <height>2436</height>
        <depth>3</depth>
    </size>
    <object>
        <name>Rating</name>
        <difficult>0</difficult>
        <bndbox>
            <xmin>310</xmin>
            <ymin>2097</ymin>
            <xmax>634</xmax>
            <ymax>2166</ymax>
        </bndbox>
    </object>
    <object>
        <name>Rating</name>
        <difficult>0</difficult>
        <bndbox>
            <xmin>302</xmin>
            <ymin>1675</ymin>
            <xmax>655</xmax>
            <ymax>1746</ymax>
        </bndbox>
    </object>
    <object>
        <name>Rating</name>
        <difficult>0</difficult>
        <bndbox>
            <xmin>321</xmin>
            <ymin>1172</ymin>
            <xmax>688</xmax>
            <ymax>1229</ymax>
        </bndbox>
    </object>
    <object>
        <name>FAB (Floating Action Button)</name>
        <difficult>0</difficult>
        <bndbox>
            <xmin>994</xmin>
            <ymin>834</ymin>
            <xmax>1114</xmax>
            <ymax>960</ymax>
        </bndbox>
    </object>
    <object>
        <name>Buttons</name>
        <difficult>0</difficult>
        <bndbox>
            <xmin>975</xmin>
            <ymin>139</ymin>
            <xmax>1087</xmax>
            <ymax>253</ymax>
        </bndbox>
    </object>
    <object>
        <name>Buttons</name>
        <difficult>0</difficult>
        <bndbox>
            <xmin>829</xmin>
            <ymin>135</ymin>
            <xmax>953</xmax>
            <ymax>253</ymax>
        </bndbox>
    </object>
</annotation>