<annotation>
    <folder>training</folder>
    <filename>34112989cb9457520df76c0eb63593419786e980.jpeg</filename>
    <size>
        <width>1125</width>
        <height>2436</height>
        <depth>3</depth>
    </size>
    <object>
        <name>Buttons</name>
        <difficult>0</difficult>
        <bndbox>
            <xmin>42</xmin>
            <ymin>2191</ymin>
            <xmax>122</xmax>
            <ymax>2268</ymax>
        </bndbox>
    </object>
    <object>
        <name>Sliders</name>
        <difficult>0</difficult>
        <bndbox>
            <xmin>84</xmin>
            <ymin>2062</ymin>
            <xmax>1052</xmax>
            <ymax>2164</ymax>
        </bndbox>
    </object>
    <object>
        <name>Buttons</name>
        <difficult>0</difficult>
        <bndbox>
            <xmin>723</xmin>
            <ymin>1698</ymin>
            <xmax>850</xmax>
            <ymax>1835</ymax>
        </bndbox>
    </object>
    <object>
        <name>Buttons</name>
        <difficult>0</difficult>
        <bndbox>
            <xmin>482</xmin>
            <ymin>1690</ymin>
            <xmax>659</xmax>
            <ymax>1830</ymax>
        </bndbox>
    </object>
    <object>
        <name>Buttons</name>
        <difficult>0</difficult>
        <bndbox>
            <xmin>282</xmin>
            <ymin>1691</ymin>
            <xmax>419</xmax>
            <ymax>1835</ymax>
        </bndbox>
    </object>
    <object>
        <name>Sliders</name>
        <difficult>0</difficult>
        <bndbox>
            <xmin>44</xmin>
            <ymin>1486</ymin>
            <xmax>1078</xmax>
            <ymax>1592</ymax>
        </bndbox>
    </object>
    <object>
        <name>Buttons</name>
        <difficult>0</difficult>
        <bndbox>
            <xmin>1005</xmin>
            <ymin>139</ymin>
            <xmax>1093</xmax>
            <ymax>228</ymax>
        </bndbox>
    </object>
</annotation>