<annotation>
    <folder>training</folder>
    <filename>f99ab399a57d39dd832acb70b029bc9e4cba325c.jpeg</filename>
    <size>
        <width>1125</width>
        <height>2436</height>
        <depth>3</depth>
    </size>
    <object>
        <name>Rating</name>
        <difficult>0</difficult>
        <bndbox>
            <xmin>53</xmin>
            <ymin>1931</ymin>
            <xmax>444</xmax>
            <ymax>1995</ymax>
        </bndbox>
    </object>
    <object>
        <name>Buttons</name>
        <difficult>0</difficult>
        <bndbox>
            <xmin>51</xmin>
            <ymin>2024</ymin>
            <xmax>452</xmax>
            <ymax>2117</ymax>
        </bndbox>
    </object>
    <object>
        <name>Buttons</name>
        <difficult>0</difficult>
        <bndbox>
            <xmin>560</xmin>
            <ymin>2173</ymin>
            <xmax>1068</xmax>
            <ymax>2346</ymax>
        </bndbox>
    </object>
    <object>
        <name>Buttons</name>
        <difficult>0</difficult>
        <bndbox>
            <xmin>941</xmin>
            <ymin>1293</ymin>
            <xmax>1067</xmax>
            <ymax>1409</ymax>
        </bndbox>
    </object>
    <object>
        <name>Buttons</name>
        <difficult>0</difficult>
        <bndbox>
            <xmin>971</xmin>
            <ymin>139</ymin>
            <xmax>1093</xmax>
            <ymax>255</ymax>
        </bndbox>
    </object>
    <object>
        <name>Buttons</name>
        <difficult>0</difficult>
        <bndbox>
            <xmin>842</xmin>
            <ymin>139</ymin>
            <xmax>939</xmax>
            <ymax>255</ymax>
        </bndbox>
    </object>
    <object>
        <name>Buttons</name>
        <difficult>0</difficult>
        <bndbox>
            <xmin>671</xmin>
            <ymin>140</ymin>
            <xmax>798</xmax>
            <ymax>255</ymax>
        </bndbox>
    </object>
    <object>
        <name>Buttons</name>
        <difficult>0</difficult>
        <bndbox>
            <xmin>1</xmin>
            <ymin>141</ymin>
            <xmax>121</xmax>
            <ymax>250</ymax>
        </bndbox>
    </object>
</annotation>